__builtins__.pyi
_thread.pyi
argparse.pyi
binascii.pyi
btree.pyi
cmath.pyi
cryptolib.pyi
deflate.pyi
errno.pyi
ffi.pyi
framebuf.pyi
gc.pyi
hashlib.pyi
heapq.pyi
machine.pyi
math.pyi
micropython.pyi
mip/__init__.pyi
mip/__main__.pyi
platform.pyi
random.pyi
requests/__init__.pyi
select.pyi
socket.pyi
termios.pyi
time.pyi
tls.pyi
uarray.pyi
uasyncio.pyi
ubinascii.pyi
ubluetooth.pyi
ucollections.pyi
ucryptolib.pyi
uctypes.pyi
uerrno.pyi
uhashlib.pyi
uheapq.pyi
uio.pyi
ujson.pyi
umachine.pyi
uos.pyi
uplatform.pyi
urandom.pyi
ure.pyi
uselect.pyi
usocket.pyi
ussl.pyi
ustruct.pyi
usys.pyi
utime.pyi
uwebsocket.pyi
uzlib.pyi
vfs.pyi
websocket.pyi
micropython_unix_stubs-1.26.0.post1.dist-info/LICENSE.md
micropython_unix_stubs-1.26.0.post1.dist-info/METADATA
micropython_unix_stubs-1.26.0.post1.dist-info/WHEEL
micropython_unix_stubs-1.26.0.post1.dist-info/RECORD
